multitfa/__init__.py
multitfa/_version.py
multitfa/helpers.py
multitfa/analysis/__init__.py
multitfa/analysis/sampling.py
multitfa/analysis/sampling_util.py
multitfa/analysis/variability.py
multitfa/core/__init__.py
multitfa/core/compound.py
multitfa/core/reaction.py
multitfa/core/solution.py
multitfa/core/tmodel.py
multitfa/data/__init__.py
multitfa/data/component_data.npz
multitfa/data/compounds_cache.pickle
multitfa/util/__init__.py
multitfa/util/constraints.py
multitfa/util/linalg_fun.py
multitfa/util/thermo_constants.py
multitfa/util/util_func.py
multitfa-0.1.2.dist-info/LICENSE
multitfa-0.1.2.dist-info/METADATA
multitfa-0.1.2.dist-info/WHEEL
multitfa-0.1.2.dist-info/top_level.txt
multitfa-0.1.2.dist-info/zip-safe
multitfa-0.1.2.dist-info/RECORD
