Metadata-Version: 2.1
Name: multitfa
Version: 0.1.2
Summary: Multivariate thermodynamics-based metabolic flux analysis in Python.
Home-page: https://github.com/biosustain/multitfa
Author: Vishnuvardhan Mahamkali
Author-email: v.mahamkali@uq.edu.au
License: Apache-2.0
Download-URL: https://pypi.org/project/multitfa/
Project-URL: Source Code, https://github.com/biosustain/multitfa
Project-URL: Documentation, https://multitfa.readthedocs.io
Project-URL: Bug Tracker, https://github.com/biosustain/multitfa/issues
Keywords: thermodynamics,multivariate,flux analysis,metabolic,TMFA,TFA,multiTFA
Platform: UNKNOWN
Classifier: Development Status :: 4 - Beta
Classifier: Intended Audience :: Science/Research
Classifier: License :: OSI Approved :: Apache Software License
Classifier: Natural Language :: English
Classifier: Operating System :: OS Independent
Classifier: Programming Language :: Python :: 3.6
Classifier: Programming Language :: Python :: 3.7
Classifier: Programming Language :: Python :: 3.8
Classifier: Programming Language :: Python :: 3 :: Only
Classifier: Topic :: Scientific/Engineering :: Bio-Informatics
Requires-Python: >=3.6
Requires-Dist: cobra
Requires-Dist: depinfo
Requires-Dist: optlang (<1.4.6)
Requires-Dist: numpy
Requires-Dist: scipy
Requires-Dist: pandas
Requires-Dist: equilibrator-api (==0.3.2b7)
Requires-Dist: component-contribution (==0.3.2b4)
Requires-Dist: equilibrator-cache (==0.3.2b2)
Provides-Extra: development
Requires-Dist: black ; extra == 'development'
Requires-Dist: isort ; extra == 'development'
Requires-Dist: pep517 ; extra == 'development'
Requires-Dist: tox ; extra == 'development'
Requires-Dist: twine ; extra == 'development'
